telebot_lite/__init__.py
telebot_lite/_version.py
telebot_lite/manage.py
telebot_lite/core/celery.py
telebot_lite/core/client.py
telebot_lite/core/exception.py
telebot_lite/core/methods.py
telebot_lite/core/updates.py
telebot_lite/db/models.py
telebot_lite/db/orm/__init__.py
telebot_lite/db/orm/init.py
telebot_lite/db/orm/mixin/__init__.py
telebot_lite/db/orm/mixin/mixin_timstamp.py
telebot_lite/db/orm/models/__init__.py
telebot_lite/db/orm/models/user.py
telebot_lite/db/orm/utils/__init__.py
telebot_lite/db/orm/utils/timezone.py
telebot_lite/test/test_send_message.py
telebot_lite/utils/__init__.py
telebot_lite/utils/load_settings.py
telebot_lite/utils/tasks/__init__.py
telebot_lite/utils/tasks/delete_task.py
telebot_lite-0.1.0.dist-info/METADATA
telebot_lite-0.1.0.dist-info/WHEEL
telebot_lite-0.1.0.dist-info/RECORD
