Metadata-Version: 2.4
Name: telebot-lite
Version: 0.1.0
Summary: A lightweight async wrapper for Telegram Bot API 9.0
Project-URL: Homepage, https://github.com/alireza_sarami/telebot-lite
Author-email: Alireza Sarami <alirs1997@gmail.com>
Requires-Python: >=3.9
Requires-Dist: asyncpg>=0.28.0
Requires-Dist: httpx<0.28,>=0.27
Requires-Dist: pydantic<3.0,>=2.8
Requires-Dist: tortoise-orm<1.0,>=0.20.0
Provides-Extra: dev
Requires-Dist: mypy; extra == 'dev'
Requires-Dist: pytest; extra == 'dev'
Requires-Dist: ruff; extra == 'dev'
